mayfpayapi/__init__.py
mayfpayapi/mayfpayapi.py
mayfpayapi-1.5.2.dist-info/METADATA
mayfpayapi-1.5.2.dist-info/WHEEL
mayfpayapi-1.5.2.dist-info/top_level.txt
mayfpayapi-1.5.2.dist-info/RECORD
