Metadata-Version: 2.1
Name: mayfpayapi
Version: 1.5.2
Summary: MayfPayApi is a Python library for interacting with the MayfPay payment system API. It provides methods for retrieving kassa balances, creating and checking invoices.
Home-page: https://github.com/MAYFPAY/MayfPayApi
Author: MayfPay
Author-email: support@mayfpay.top
Project-URL: Source, https://github.com/MAYFPAY/MayfPayApi
Project-URL: Documentation, https://mayfpay.top/docs
Project-URL: Bug Reports, https://github.com/MAYFPAY/MayfPayApi/issues
Requires-Dist: requests
